mongofiles.py
setup.py
mongofiles.egg-info/PKG-INFO
mongofiles.egg-info/SOURCES.txt
mongofiles.egg-info/dependency_links.txt
mongofiles.egg-info/top_level.txt