Metadata-Version: 1.0
Name: mongofiles
Version: 1.0
Summary: mongofiles for Humans
Home-page: https://github.com/shuge/mongofiles
Author: Shuge Lee
Author-email: shuge.lee@gmail.com
License: MIT License
Platform: UNKNOWN
